Verilog_Folder/CPU/ALU.v
module ALU (
	input wire [15 : 0] inDataA, inDataB,
	input wire [3 : 0] aluCode,
	output reg [15 : 0] aluData,
	output reg ifBan
);

	initial
	begin
		ifBan = 0;
		aluData = 0;
	end

	always @*
	begin
		case (aluCode)
			4'b0000: aluData = 0;
			4'b0001: aluData = ~inDataA;
			4'b0010: aluData = (inDataA >>> 1);
			4'b0011: aluData = {inDataA[14 : 0], inDataA[15]};
			4'b0100: aluData = inDataA + inDataB;
			4'b0101: aluData = inDataA;
			4'b0110: aluData = inDataB;
			4'b0111: ifBan = inDataA[15] == 1 ? 1 : 0;
			default: aluData = 1'bX;
		endcase
	end
endmodule

Verilog_Folder/CPU/CTRLUNIT.v
module CTRLUNIT (
	input wire [3 : 0] ins,
	output reg stop, pcWR, accWR, memWR,
	output reg [3 : 0] aluCode
);

	initial
	begin
		stop = 0;
		pcWR = 0;
		accWR = 0;
		memWR = 0;
		aluCode = 4'bX;
	end

	always @(ins)
	begin

		if (ins[3] == 0)
		begin
			case (ins[3 : 2])
				2'b00: {stop, pcWR, accWR, memWR, aluCode} = 8'b00100100;		//000	add
				2'b01: {stop, pcWR, accWR, memWR, aluCode} = 8'b00010101;		//001	sta
				2'b10: {stop, pcWR, accWR, memWR, aluCode} = 8'b00100110;		//010	lda
				2'b11: {stop, pcWR, accWR, memWR, aluCode} = 8'b00100000;		//011	cla
			endcase
		end
		else
		begin
			if (ins[2] == 0)
			begin
				if (ins[1] == 0)
				begin
					{stop, pcWR, accWR, memWR, aluCode} = 8'b00100001;			//100	com
				end
				else
				begin
					{stop, pcWR, accWR, memWR, aluCode} = 8'b01001111;			//101	jmp
				end
			end
			else
			begin
				case (ins[1 : 0])
					2'b00: {stop, pcWR, accWR, memWR, aluCode} = 8'b00100111;	//1100	ban
					2'b01: {stop, pcWR, accWR, memWR, aluCode} = 8'b00100010;	//1101	shr
					2'b10: {stop, pcWR, accWR, memWR, aluCode} = 8'b00100011;	//1110	csl
					2'b11: {stop, pcWR, accWR, memWR, aluCode} = 8'b10001111;	//1111	stp
				endcase
			end
		end
	end

endmodule

Verilog_Folder/CPU/MEMOR.v
module MEMOR (
	input memWR, clk,
	input wire [7 : 0] Addr,
	input wire [15 : 0] inData,
	output wire [15 : 0] outData
);

	reg [15 : 0] unit [8'b11111111 : 0];

	assign outData = unit[Addr];

	initial
	begin
		unit[0] = 16'h0002;
		unit[1] = 16'h8000;
		unit[2] = 16'h0001;
	end

	always @(negedge clk)
	begin
		if (memWR == 1)
			unit[Addr] = inData;
	end
endmodule

Verilog_Folder/CPU/ACC.v
module ACC (
	input wire clk, accWR,
	input wire [15 : 0] inData,
	output wire [15 : 0] outData
);

	reg [15 : 0] accData;

	assign outData = accData;

	initial
	begin
		accData = 0;
	end

	always @(negedge clk)
	begin
		if (accWR == 1)
			accData = inData;
	end

endmodule

Verilog_Folder/CPU/INSREG.v
module INSREG (
	input wire [7 : 0] Addr,
	output reg [11 : 0] ins
);

	reg [11 : 0] unit[8'b11111111:0];

	initial
	begin
		unit[0] = 12'b010000000001;		//lda
		unit[1] = 12'b000000000010;		//add
		unit[2] = 12'b110100000000;		//shr
		unit[3] = 12'b000000000010;		//add
		unit[4] = 12'b000000000010;		//add
		unit[5] = 12'b000000000001;		//add
		unit[6] = 12'b001000000010;		//sta
		unit[7] = 12'b101000000001;		//jmp
		unit[8] = 12'b110000000010;		//ban
		unit[9] = 12'b111100000000;		//stp
	end

	always @*
	begin
		ins = unit[Addr];
	end

endmodule

Verilog_Folder/CPU/PC.v
module PC (
	input wire clk, rst, stop, pcWR, ifBan,
	input wire [7 : 0] jump,
	output reg [7 : 0] Addr
);

	initial
	begin
		Addr = 0;
	end

	always @*
	begin
		if (stop == 0)
		begin
			if (rst == 1)
			begin
				Addr = 0;
			end
		end
	end

	always @(posedge clk)
	begin
		if (stop == 0)
		begin
			Addr = Addr + 1;
		end
	end

	always @(negedge clk)
	begin
		if (stop == 0)
		begin
			if (pcWR == 1)
			begin
				Addr = jump - 1;
			end
			if (ifBan ==  1)
			begin
				Addr = Addr + jump - 1;
			end
		end
	end
	
endmodule

Verilog_Folder/CPU/CPU.v
`include "PC.v"
`include "INSREG.v"
`include "ACC.v"
`include "MEMOR.v"
`include "CTRLUNIT.v"
`include "ALU.v"

module CPU (
	input wire clk, rst
);

	wire stop, pcWR, accWR, memWR, ifBan;
	wire [3 : 0] aluCode;
	wire [7 : 0] Addr;
	wire [11 : 0] ins;
	wire [15 : 0] inDataA, inDataB, aluData;

	PC pc (
		.clk(clk), .rst(rst), .stop(stop), .pcWR(pcWR), .ifBan(ifBan),
		.jump(ins[7 : 0]), .Addr(Addr)
	);

	INSREG insreg (
		.Addr(Addr), .ins(ins)
	);

	ACC acc (
		.clk(clk), .accWR(accWR),
		.inData(aluData),
		.outData(inDataA)
	);

	MEMOR memor (
		.memWR(memWR), .clk(clk),
		.Addr(ins[7 : 0]),
		.inData(aluData),
		.outData(inDataB)
	);

	CTRLUNIT cu (
		.ins(ins[11 : 8]),
		.stop(stop), .pcWR(pcWR), .accWR(accWR), .memWR(memWR),
		.aluCode(aluCode)
	);

	ALU alu (
		.aluCode(aluCode),
		.inDataA(inDataA), .inDataB(inDataB),
		.ifBan(ifBan),
		.aluData(aluData)
	);

endmodule

Verilog_Folder/CPU/CPU_TB.v
`include "CPU.v"

module CPU_TB;
	reg clk, rst;

	initial
	begin
		$dumpfile("test.vcd");
		$dumpvars(0, CPU_TB);
		clk = 1;
		rst = 0;

		#1
		rst = ~rst;

		#1
		rst = ~rst;

		#18
		$stop;
	end

	always #1
	begin
		clk = ~clk;
	end

	CPU cpu (
		.clk(clk), .rst(rst)
	);

endmodule

Verilog_Folder/CPU/test.vcd
$date
	Mon Dec 28 17:15:01 2020
$end
$version
	Icarus Verilog
$end
$timescale
	1s
$end
$scope module CPU_TB $end
$var reg 1 ! clk $end
$var reg 1 " rst $end
$scope module cpu $end
$var wire 1 ! clk $end
$var wire 1 " rst $end
$var wire 1 # stop $end
$var wire 1 $ pcWR $end
$var wire 1 % memWR $end
$var wire 12 & ins [11:0] $end
$var wire 16 ' inDataB [15:0] $end
$var wire 16 ( inDataA [15:0] $end
$var wire 1 ) ifBan $end
$var wire 16 * aluData [15:0] $end
$var wire 4 + aluCode [3:0] $end
$var wire 1 , accWR $end
$var wire 8 - Addr [7:0] $end
$scope module acc $end
$var wire 1 ! clk $end
$var wire 16 . outData [15:0] $end
$var wire 16 / inData [15:0] $end
$var wire 1 , accWR $end
$var reg 16 0 accData [15:0] $end
$upscope $end
$scope module alu $end
$var wire 16 1 inDataA [15:0] $end
$var wire 16 2 inDataB [15:0] $end
$var wire 4 3 aluCode [3:0] $end
$var reg 16 4 aluData [15:0] $end
$var reg 1 ) ifBan $end
$upscope $end
$scope module cu $end
$var wire 4 5 ins [3:0] $end
$var reg 1 , accWR $end
$var reg 4 6 aluCode [3:0] $end
$var reg 1 % memWR $end
$var reg 1 $ pcWR $end
$var reg 1 # stop $end
$upscope $end
$scope module insreg $end
$var wire 8 7 Addr [7:0] $end
$var reg 12 8 ins [11:0] $end
$upscope $end
$scope module memor $end
$var wire 8 9 Addr [7:0] $end
$var wire 1 ! clk $end
$var wire 16 : inData [15:0] $end
$var wire 1 % memWR $end
$var wire 16 ; outData [15:0] $end
$upscope $end
$scope module pc $end
$var wire 1 ! clk $end
$var wire 1 ) ifBan $end
$var wire 8 < jump [7:0] $end
$var wire 1 $ pcWR $end
$var wire 1 " rst $end
$var wire 1 # stop $end
$var reg 8 = Addr [7:0] $end
$upscope $end
$upscope $end
$upscope $end
$enddefinitions $end
#0
$dumpvars
b1 =
b10 <
b1 ;
b1 :
b10 9
b10 8
b1 7
b100 6
b0 5
b1 4
b100 3
b1 2
b0 1
b0 0
b1 /
b0 .
b1 -
1,
b100 +
b1 *
0)
b0 (
b1 '
b10 &
0%
0$
0#
0"
1!
$end
#1
0,
1%
b101 +
b101 3
b101 6
b100 5
b1000000000000000 '
b1000000000000000 2
b1000000000000000 ;
b1 9
b1 <
b1 *
b1 /
b1 4
b1 :
b10000000001 &
b10000000001 8
b1 (
b1 .
b1 1
b1 0
b0 -
b0 7
b0 =
0!
1"
#2
b10 *
b10 /
b10 4
b10 :
1,
0%
b100 +
b100 3
b100 6
b0 5
b1 '
b1 2
b1 ;
b10 9
b10 <
b10 &
b10 8
b1 -
b1 7
b1 =
1!
0"
#3
b11 *
b11 /
b11 4
b11 :
b10 (
b10 .
b10 1
b10 0
0!
#4
b10 +
b10 3
b10 6
b1 *
b1 /
b1 4
b1 :
b1101 5
b10 '
b10 2
b10 ;
b0 9
b0 <
b110100000000 &
b110100000000 8
b10 -
b10 7
b10 =
1!
#5
b0 *
b0 /
b0 4
b0 :
b1 (
b1 .
b1 1
b1 0
0!
#6
b10 *
b10 /
b10 4
b10 :
b100 +
b100 3
b100 6
b0 5
b1 '
b1 2
b1 ;
b10 9
b10 <
b10 &
b10 8
b11 -
b11 7
b11 =
1!
#7
b11 *
b11 /
b11 4
b11 :
b10 (
b10 .
b10 1
b10 0
0!
#8
b100 -
b100 7
b100 =
1!
#9
b100 *
b100 /
b100 4
b100 :
b11 (
b11 .
b11 1
b11 0
0!
#10
b1000000000000011 *
b1000000000000011 /
b1000000000000011 4
b1000000000000011 :
b1000000000000000 '
b1000000000000000 2
b1000000000000000 ;
b1 9
b1 <
b1 &
b1 8
b101 -
b101 7
b101 =
1!
#11
b11 *
b11 /
b11 4
b11 :
b1000000000000011 (
b1000000000000011 .
b1000000000000011 1
b1000000000000011 0
0!
#12
b1000000000000100 *
b1000000000000100 /
b1000000000000100 4
b1000000000000100 :
b10 5
b1 '
b1 2
b1 ;
b10 9
b10 <
b1000000010 &
b1000000010 8
b110 -
b110 7
b110 =
1!
#13
b1000000000000101 *
b1000000000000101 /
b1000000000000101 4
b1000000000000101 :
b1000000000000100 (
b1000000000000100 .
b1000000000000100 1
b1000000000000100 0
0!
#14
1$
0,
b1111 +
b1111 3
b1111 6
b0x *
b0x /
b0x 4
b0x :
b1010 5
b1000000000000000 '
b1000000000000000 2
b1000000000000000 ;
b1 9
b1 <
b101000000001 &
b101000000001 8
b111 -
b111 7
b111 =
1!
#15
b1000000000000100 *
b1000000000000100 /
b1000000000000100 4
b1000000000000100 :
0$
1%
b101 +
b101 3
b101 6
b100 5
b10000000001 &
b10000000001 8
b0 -
b0 7
b0 =
0!
#16
b1000000000000101 *
b1000000000000101 /
b1000000000000101 4
b1000000000000101 :
1,
0%
b100 +
b100 3
b100 6
b0 5
b1 '
b1 2
b1 ;
b10 9
b10 <
b10 &
b10 8
b1 -
b1 7
b1 =
1!
#17
b1000000000000110 *
b1000000000000110 /
b1000000000000110 4
b1000000000000110 :
b1000000000000101 (
b1000000000000101 .
b1000000000000101 1
b1000000000000101 0
0!
#18
b10 +
b10 3
b10 6
b100000000000010 *
b100000000000010 /
b100000000000010 4
b100000000000010 :
b1101 5
b10 '
b10 2
b10 ;
b0 9
b0 <
b110100000000 &
b110100000000 8
b10 -
b10 7
b10 =
1!
#19
b10000000000001 *
b10000000000001 /
b10000000000001 4
b10000000000001 :
b100000000000010 (
b100000000000010 .
b100000000000010 1
b100000000000010 0
0!
